{"status":"success","session_id":"69ae8849b7cfb6b3cc210e8a","phase":"task_model_completed","task_spec":{"Domain":"用户未指定","Target_object":"用户未指定","Spatial_scope":{"description":"用户未指定","bbox":[],"crs_requirement":"不限","spatial_resolution":"不限"},"Temporal_scope":{"description":"用户未指定","start_time":"用户未指定","end_time":"用户未指定","temporal_resolution":"用户未指定","is_realtime":false},"Resolution_requirements":{"spatial":"用户未指定","temporal":"用户未指定","numerical":"用户未指定","priority":"用户未指定"},"Additional_constraints":{"data_quality":"用户未指定","computation_constraints":"用户未指定","output_format":"用户未指定","other":"用户未指定"}},"model_contract":{"Required_slots":[{"Input_name":"research_range","Semantic_requirement":"研究区范围数据 (中国苏州市)","Data_type":"Vector","Spatial_requirement":{"Region":"中国苏州市 (bbox: [120.0, 30.7, 121.3, 32.0])，空间分辨率不低于30米","Crs":"不限"},"Temporal_requirement":"模拟期内静态边界","Format_requirement":"Shapefile, GeoJSON"},{"Input_name":"research_restriction","Semantic_requirement":"研究区约束数据 (如生态红线、永久基本农田等)","Data_type":"Vector","Spatial_requirement":{"Region":"中国苏州市 (bbox: [120.0, 30.7, 121.3, 32.0])，空间分辨率不低于30米","Crs":"不限"},"Temporal_requirement":"应与模拟年份相匹配或在模拟期间保持有效","Format_requirement":"Shapefile, GeoJSON"},{"Input_name":"history_land_data","Semantic_requirement":"历史土地利用数据 (包含城市用地分类，用于模型训练和驱动)","Data_type":"Raster","Spatial_requirement":{"Region":"中国苏州市 (bbox: [120.0, 30.7, 121.3, 32.0])，空间分辨率不低于30米","Crs":"不限"},"Temporal_requirement":"覆盖训练期，例如从 `st_year` 到 `first_sim_year - 1` 的每年或数年间隔数据","Format_requirement":"压缩文件 (如ZIP, RAR) 内含 GeoTIFF 系列栅格数据"},{"Input_name":"slope_data","Semantic_requirement":"坡度空间变量数据","Data_type":"Raster","Spatial_requirement":{"Region":"中国苏州市 (bbox: [120.0, 30.7, 121.3, 32.0])，空间分辨率与土地利用数据保持一致或匹配","Crs":"不限"},"Temporal_requirement":"模拟期内相对静态数据 (如基于DEM生成，取某一代表年份)","Format_requirement":"GeoTIFF"},{"Input_name":"dist_town_data","Semantic_requirement":"距离镇中心距离空间变量数据","Data_type":"Raster","Spatial_requirement":{"Region":"中国苏州市 (bbox: [120.0, 30.7, 121.3, 32.0])，空间分辨率与土地利用数据保持一致或匹配","Crs":"不限"},"Temporal_requirement":"模拟期内相对静态数据 (取某一代表年份)","Format_requirement":"GeoTIFF"},{"Input_name":"dist_county_data","Semantic_requirement":"距离县中心距离空间变量数据","Data_type":"Raster","Spatial_requirement":{"Region":"中国苏州市 (bbox: [120.0, 30.7, 121.3, 32.0])，空间分辨率与土地利用数据保持一致或匹配","Crs":"不限"},"Temporal_requirement":"模拟期内相对静态数据 (取某一代表年份)","Format_requirement":"GeoTIFF"},{"Input_name":"st_year","Semantic_requirement":"模型训练数据起始年份","Data_type":"Parameter","Spatial_requirement":{"Region":"N/A","Crs":"N/A"},"Temporal_requirement":"特定年份 (整数)","Format_requirement":"N/A"},{"Input_name":"first_sim_year","Semantic_requirement":"第一个模拟年份 (预测起始年份)","Data_type":"Parameter","Spatial_requirement":{"Region":"N/A","Crs":"N/A"},"Temporal_requirement":"特定年份 (整数)","Format_requirement":"N/A"},{"Input_name":"out_len","Semantic_requirement":"预测年份数目","Data_type":"Parameter","Spatial_requirement":{"Region":"N/A","Crs":"N/A"},"Temporal_requirement":"N/A","Format_requirement":"N/A"},{"Input_name":"land_demands","Semantic_requirement":"每个预测年份的城市用地需求增量 (栅格数量)","Data_type":"Parameter","Spatial_requirement":{"Region":"N/A","Crs":"N/A"},"Temporal_requirement":"覆盖预测期，从 `first_sim_year` 到 `first_sim_year + out_len - 1` 的每年需求量","Format_requirement":"字符串 (以英文逗号分隔的整数列表)"}]},"required_inputs":[{"Input_name":"research_range","Semantic_requirement":"研究区范围数据 (中国苏州市)","Data_type":"Vector","Spatial_requirement":{"Region":"中国苏州市 (bbox: [120.0, 30.7, 121.3, 32.0])，空间分辨率不低于30米","Crs":"不限"},"Temporal_requirement":"模拟期内静态边界","Format_requirement":"Shapefile, GeoJSON"},{"Input_name":"research_restriction","Semantic_requirement":"研究区约束数据 (如生态红线、永久基本农田等)","Data_type":"Vector","Spatial_requirement":{"Region":"中国苏州市 (bbox: [120.0, 30.7, 121.3, 32.0])，空间分辨率不低于30米","Crs":"不限"},"Temporal_requirement":"应与模拟年份相匹配或在模拟期间保持有效","Format_requirement":"Shapefile, GeoJSON"},{"Input_name":"history_land_data","Semantic_requirement":"历史土地利用数据 (包含城市用地分类，用于模型训练和驱动)","Data_type":"Raster","Spatial_requirement":{"Region":"中国苏州市 (bbox: [120.0, 30.7, 121.3, 32.0])，空间分辨率不低于30米","Crs":"不限"},"Temporal_requirement":"覆盖训练期，例如从 `st_year` 到 `first_sim_year - 1` 的每年或数年间隔数据","Format_requirement":"压缩文件 (如ZIP, RAR) 内含 GeoTIFF 系列栅格数据"},{"Input_name":"slope_data","Semantic_requirement":"坡度空间变量数据","Data_type":"Raster","Spatial_requirement":{"Region":"中国苏州市 (bbox: [120.0, 30.7, 121.3, 32.0])，空间分辨率与土地利用数据保持一致或匹配","Crs":"不限"},"Temporal_requirement":"模拟期内相对静态数据 (如基于DEM生成，取某一代表年份)","Format_requirement":"GeoTIFF"},{"Input_name":"dist_town_data","Semantic_requirement":"距离镇中心距离空间变量数据","Data_type":"Raster","Spatial_requirement":{"Region":"中国苏州市 (bbox: [120.0, 30.7, 121.3, 32.0])，空间分辨率与土地利用数据保持一致或匹配","Crs":"不限"},"Temporal_requirement":"模拟期内相对静态数据 (取某一代表年份)","Format_requirement":"GeoTIFF"},{"Input_name":"dist_county_data","Semantic_requirement":"距离县中心距离空间变量数据","Data_type":"Raster","Spatial_requirement":{"Region":"中国苏州市 (bbox: [120.0, 30.7, 121.3, 32.0])，空间分辨率与土地利用数据保持一致或匹配","Crs":"不限"},"Temporal_requirement":"模拟期内相对静态数据 (取某一代表年份)","Format_requirement":"GeoTIFF"},{"Input_name":"st_year","Semantic_requirement":"模型训练数据起始年份","Data_type":"Parameter","Spatial_requirement":{"Region":"N/A","Crs":"N/A"},"Temporal_requirement":"特定年份 (整数)","Format_requirement":"N/A"},{"Input_name":"first_sim_year","Semantic_requirement":"第一个模拟年份 (预测起始年份)","Data_type":"Parameter","Spatial_requirement":{"Region":"N/A","Crs":"N/A"},"Temporal_requirement":"特定年份 (整数)","Format_requirement":"N/A"},{"Input_name":"out_len","Semantic_requirement":"预测年份数目","Data_type":"Parameter","Spatial_requirement":{"Region":"N/A","Crs":"N/A"},"Temporal_requirement":"N/A","Format_requirement":"N/A"},{"Input_name":"land_demands","Semantic_requirement":"每个预测年份的城市用地需求增量 (栅格数量)","Data_type":"Parameter","Spatial_requirement":{"Region":"N/A","Crs":"N/A"},"Temporal_requirement":"覆盖预测期，从 `first_sim_year` 到 `first_sim_year + out_len - 1` 的每年需求量","Format_requirement":"字符串 (以英文逗号分隔的整数列表)"}],"data_profiles":[],"alignment_result":{},"alignment_status":"pending","can_run_now":false,"go_no_go":"pending","recommended_actions":["请先上传模型所需数据后调用 /api/triangle-matching/scan-and-align","如需预览上传数据结构，可先调用 /api/triangle-matching/scan-data"],"minimal_runnable_inputs":[],"mapping_plan_draft":[],"execution_estimate":{},"completed_at":null,"message":"任务解析完成，请上传模型所需数据后调用扫描接口"}